{
   "packages": [
      {
         "name": "rp2040",
         "maintainer": "Earle F. Philhower, III",
         "websiteURL": "https://github.com/earlephilhower/arduino-pico",
         "email": "earlephilhower@yahoo.com",
         "help": {
            "online": "https://arduino-pico.readthedocs.io/en/latest/"
         },
         "platforms": [
            {
               "category": "Raspberry Pi Pico",
               "name": "Raspberry Pi Pico/RP2040",
               "url": "",
               "version": "",
               "architecture": "rp2040",
               "archiveFileName": "",
               "boards": [
                  {
                     "name": "Raspberry Pi Pico"
                  },
                  {
                     "name": "Adafruit Feather RP2040"
                  },
                  {
                     "name": "Adafruit ItsyBitsy RP2040"
                  },
                  {
                     "name": "Adafruit KB2040"
                  },
                  {
                     "name": "Adafruit Macropad RP2040"
                  },
                  {
                     "name": "Adafruit QTPy RP2040"
                  },
                  {
                     "name": "Adafruit STEMMA Friend RP2040"
                  },
                  {
                     "name": "Adafruit Trinkey RP2040 QT"
                  },
                  {
                     "name": "Arduino Nano RP2040 Connect"
                  },
                  {
                     "name": "Cytron Maker Nano RP2040"
                  },
                  {
                     "name": "Cytron Maker Pi RP2040"
                  },
                  {
                     "name": "DeRuiLab FlyBoard2040 Core"
                  },
                  {
                     "name": "DFRobot Beetle RP2040"
                  },
                  {
                     "name": "Invector Labs Challenger RP2040 WiFi"
                  },
                  {
                     "name": "Invector Labs Challenger RP2040 WiFi/BLE"
                  },
                  {
                     "name": "Invector Labs Challenger NB RP2040 WiFi"
                  },
                  {
                     "name": "Invector Labs Challenger RP2040 LTE"
                  },
                  {
                     "name": "Invector Labs Challenger RP2040 LoRa"
                  },
                  {
                     "name": "Invector Labs RPICO32"
                  },
                  {
                     "name": "Seeed XIAO RP2040"
                  },
                  {
                     "name": "Solder Party RP2040 Stamp"
                  },
                  {
                     "name": "SparkFun ProMicro RP2040"
                  },
                  {
                     "name": "SparkFun Thing Plus RP2040"
                  },
                  {
                     "name": "Melopero Shake RP2040"
                  },
                  {
                     "name": "uPesy RP2040 DevKit"
                  },
                  {
                     "name": "WIZnet W5100S-EVB-Pico"
                  },
                  {
                     "name": "WIZnet 5500-EVB-Pico"
                  },
                  {
                     "name": "WIZnet WizFi360-EVB-Pico"
                  },
                  {
                     "name": "Generic RP2040 Module"
                  }
               ],
               "toolsDependencies": [
                  {
                     "packager": "rp2040",
                     "version": "1.3.4-a-ff58458",
                     "name": "pqt-gcc"
                  },
                  {
                     "packager": "rp2040",
                     "version": "1.3.4-a-ff58458",
                     "name": "pqt-mklittlefs"
                  },
                  {
                     "packager": "rp2040",
                     "version": "1.3.4-a-ff58458",
                     "name": "pqt-elf2uf2"
                  },
                  {
                     "packager": "rp2040",
                     "version": "1.3.4-a-ff58458",
                     "name": "pqt-pioasm"
                  },
                  {
                     "packager": "rp2040",
                     "version": "1.0.1-base-3a57aed",
                     "name": "pqt-python3"
                  },
                  {
                     "packager": "rp2040",
                     "version": "1.3.4-a-ff58458",
                     "name": "pqt-openocd"
                  }
               ],
               "help": {
                  "online": ""
               }
            }
         ],
         "tools": [
            {
               "version": "1.3.4-a-ff58458",
               "name": "pqt-openocd",
               "systems": [
                  {
                     "host": "aarch64-linux-gnu",
                     "url": "https://github.com/earlephilhower/pico-quick-toolchain/releases/download/1.3.4-a/aarch64-linux-gnu.openocd-e3428fadb.220606.tar.gz",
                     "archiveFileName": "aarch64-linux-gnu.openocd-e3428fadb.220606.tar.gz",
                     "checksum": "SHA-256:88f024741092136266171f45df61d55cd760708593d01a613e233c4b5e9d9ed9",
                     "size": "5607141"
                  },
                  {
                     "host": "arm-linux-gnueabihf",
                     "url": "https://github.com/earlephilhower/pico-quick-toolchain/releases/download/1.3.4-a/arm-linux-gnueabihf.openocd-e3428fadb.220606.tar.gz",
                     "archiveFileName": "arm-linux-gnueabihf.openocd-e3428fadb.220606.tar.gz",
                     "checksum": "SHA-256:4203c3f89c71e722c6a2c0764e52d8b56b0d8bd45cbd3c7ccdfeea1b5dd45e95",
                     "size": "5344176"
                  },
                  {
                     "host": "i686-pc-linux-gnu",
                     "url": "https://github.com/earlephilhower/pico-quick-toolchain/releases/download/1.3.4-a/i686-linux-gnu.openocd-e3428fadb.220606.tar.gz",
                     "archiveFileName": "i686-linux-gnu.openocd-e3428fadb.220606.tar.gz",
                     "checksum": "SHA-256:69c602a270830a5dbb6139599fdc4f16459ed42f12d8c72a77bee3804bc176d5",
                     "size": "5168356"
                  },
                  {
                     "host": "i686-mingw32",
                     "url": "https://github.com/earlephilhower/pico-quick-toolchain/releases/download/1.3.4-a/i686-w64-mingw32.openocd-e3428fadb.220606.zip",
                     "archiveFileName": "i686-w64-mingw32.openocd-e3428fadb.220606.zip",
                     "checksum": "SHA-256:6ef401317ffafcb92bbf5d14e2b905d50863e2a670a6b065829c56fed322833e",
                     "size": "2156819"
                  },
                  {
                     "host": "x86_64-apple-darwin",
                     "url": "https://github.com/earlephilhower/pico-quick-toolchain/releases/download/1.3.4-a/x86_64-apple-darwin14.openocd-e3428fadb.220606.tar.gz",
                     "archiveFileName": "x86_64-apple-darwin14.openocd-e3428fadb.220606.tar.gz",
                     "checksum": "SHA-256:2fb06c96fcef197e15bd4f6ff3ccb94c197f80ab4dbb520dd3151cdaf4396d00",
                     "size": "2002506"
                  },
                  {
                     "host": "x86_64-pc-linux-gnu",
                     "url": "https://github.com/earlephilhower/pico-quick-toolchain/releases/download/1.3.4-a/x86_64-linux-gnu.openocd-e3428fadb.220606.tar.gz",
                     "archiveFileName": "x86_64-linux-gnu.openocd-e3428fadb.220606.tar.gz",
                     "checksum": "SHA-256:291e66e269a6d68d93625a26057a6409507f913cbf84f2b901f9711ede5ac0a8",
                     "size": "5540576"
                  },
                  {
                     "host": "x86_64-mingw32",
                     "url": "https://github.com/earlephilhower/pico-quick-toolchain/releases/download/1.3.4-a/x86_64-w64-mingw32.openocd-e3428fadb.220606.zip",
                     "archiveFileName": "x86_64-w64-mingw32.openocd-e3428fadb.220606.zip",
                     "checksum": "SHA-256:b00fa737cecf561b5ba76b0bf60f18335da0524b8c966967ec1517101d7ed12e",
                     "size": "2156820"
                  }
               ]
            },
            {
               "version": "1.0.1-base-3a57aed",
               "name": "pqt-python3",
               "systems": [
                  {
                     "host": "arm-linux-gnueabihf",
                     "url": "https://github.com/earlephilhower/pico-quick-toolchain/releases/download/1.0.1-base/python3-via-env.tar.gz",
                     "archiveFileName": "python3-via-env.tar.gz",
                     "checksum": "SHA-256:c9237bfe0f62842d7187a39495baa4a7e3ab8b87c0b433614294b023cf0bc0f3",
                     "size": "292"
                  },
                  {
                     "host": "x86_64-mingw32",
                     "url": "https://github.com/earlephilhower/pico-quick-toolchain/releases/download/1.0.1-base/python3-3.7.2.post1-embed-win32v2a.zip",
                     "archiveFileName": "python3-3.7.2.post1-embed-win32v2a.zip",
                     "checksum": "SHA-256:f57cb2daf86176d2929e7c58990c2ac32554e3219d454dcac10e464ddda35bf2",
                     "size": "6428926"
                  },
                  {
                     "host": "i686-mingw32",
                     "url": "https://github.com/earlephilhower/pico-quick-toolchain/releases/download/1.0.1-base/python3-3.7.2.post1-embed-win32v2a.zip",
                     "archiveFileName": "python3-3.7.2.post1-embed-win32v2a.zip",
                     "checksum": "SHA-256:f57cb2daf86176d2929e7c58990c2ac32554e3219d454dcac10e464ddda35bf2",
                     "size": "6428926"
                  },
                  {
                     "host": "aarch64-linux-gnu",
                     "url": "https://github.com/earlephilhower/pico-quick-toolchain/releases/download/1.0.1-base/python3-via-env.tar.gz",
                     "archiveFileName": "python3-via-env.tar.gz",
                     "checksum": "SHA-256:c9237bfe0f62842d7187a39495baa4a7e3ab8b87c0b433614294b023cf0bc0f3",
                     "size": "292"
                  },
                  {
                     "host": "arm-linux-gnueabihf",
                     "url": "https://github.com/earlephilhower/pico-quick-toolchain/releases/download/1.0.1-base/python3-via-env.tar.gz",
                     "archiveFileName": "python3-via-env.tar.gz",
                     "checksum": "SHA-256:c9237bfe0f62842d7187a39495baa4a7e3ab8b87c0b433614294b023cf0bc0f3",
                     "size": "292"
                  },
                  {
                     "host": "i686-pc-linux-gnu",
                     "url": "https://github.com/earlephilhower/pico-quick-toolchain/releases/download/1.0.1-base/python3-via-env.tar.gz",
                     "archiveFileName": "python3-via-env.tar.gz",
                     "checksum": "SHA-256:c9237bfe0f62842d7187a39495baa4a7e3ab8b87c0b433614294b023cf0bc0f3",
                     "size": "292"
                  },
                  {
                     "host": "x86_64-apple-darwin",
                     "url": "https://github.com/earlephilhower/pico-quick-toolchain/releases/download/1.0.1-base/python3-macosx-portable.tar.gz",
                     "archiveFileName": "python3-macosx-portable.tar.gz",
                     "checksum": "SHA-256:01a5bf1fa264c6f04cfaadf4c6e9f6caaacb6833ef40104dfbe953fcdb9bca1c",
                     "size": "25494144"
                  },
                  {
                     "host": "x86_64-pc-linux-gnu",
                     "url": "https://github.com/earlephilhower/pico-quick-toolchain/releases/download/1.0.1-base/python3-via-env.tar.gz",
                     "archiveFileName": "python3-via-env.tar.gz",
                     "checksum": "SHA-256:c9237bfe0f62842d7187a39495baa4a7e3ab8b87c0b433614294b023cf0bc0f3",
                     "size": "292"
                  }
               ]
            },
            {
               "version": "1.3.4-a-ff58458",
               "name": "pqt-gcc",
               "systems": [
                  {
                     "host": "aarch64-linux-gnu",
                     "url": "https://github.com/earlephilhower/pico-quick-toolchain/releases/download/1.3.4-a/aarch64-linux-gnu.arm-none-eabi-ff58458.220606.tar.gz",
                     "archiveFileName": "aarch64-linux-gnu.arm-none-eabi-ff58458.220606.tar.gz",
                     "checksum": "SHA-256:81186151c28b475d115bd594c3dc7063e491edbd228502cb0c06cbcc6e10df18",
                     "size": "102730563"
                  },
                  {
                     "host": "arm-linux-gnueabihf",
                     "url": "https://github.com/earlephilhower/pico-quick-toolchain/releases/download/1.3.4-a/arm-linux-gnueabihf.arm-none-eabi-ff58458.220606.tar.gz",
                     "archiveFileName": "arm-linux-gnueabihf.arm-none-eabi-ff58458.220606.tar.gz",
                     "checksum": "SHA-256:f73bde9acc8ded04e30582422281e8a46a3ae451c7177dee6f8312782a1b9b63",
                     "size": "95358866"
                  },
                  {
                     "host": "i686-pc-linux-gnu",
                     "url": "https://github.com/earlephilhower/pico-quick-toolchain/releases/download/1.3.4-a/i686-linux-gnu.arm-none-eabi-ff58458.220606.tar.gz",
                     "archiveFileName": "i686-linux-gnu.arm-none-eabi-ff58458.220606.tar.gz",
                     "checksum": "SHA-256:eb2ca74ead5c3536909bd355ec7e0c3ef83dbfaa102c2b8c5a23c956d72c9dc2",
                     "size": "105327715"
                  },
                  {
                     "host": "i686-mingw32",
                     "url": "https://github.com/earlephilhower/pico-quick-toolchain/releases/download/1.3.4-a/i686-w64-mingw32.arm-none-eabi-ff58458.220606.zip",
                     "archiveFileName": "i686-w64-mingw32.arm-none-eabi-ff58458.220606.zip",
                     "checksum": "SHA-256:4036645cf73580290eca32657e3879e9f9822d0b2089fc53402d324a2a5431c4",
                     "size": "105541233"
                  },
                  {
                     "host": "x86_64-apple-darwin",
                     "url": "https://github.com/earlephilhower/pico-quick-toolchain/releases/download/1.3.4-a/x86_64-apple-darwin14.arm-none-eabi-ff58458.220606.tar.gz",
                     "archiveFileName": "x86_64-apple-darwin14.arm-none-eabi-ff58458.220606.tar.gz",
                     "checksum": "SHA-256:be0b8800c52e4feb4980e73f4c5ea3feeb9f2c33ed7a47e6c439ba9e124804f1",
                     "size": "107390503"
                  },
                  {
                     "host": "x86_64-pc-linux-gnu",
                     "url": "https://github.com/earlephilhower/pico-quick-toolchain/releases/download/1.3.4-a/x86_64-linux-gnu.arm-none-eabi-ff58458.220606.tar.gz",
                     "archiveFileName": "x86_64-linux-gnu.arm-none-eabi-ff58458.220606.tar.gz",
                     "checksum": "SHA-256:205e3b4239821ba4708687d009d457922d3d8bf42952a8841e6f9140c61a05df",
                     "size": "106720531"
                  },
                  {
                     "host": "x86_64-mingw32",
                     "url": "https://github.com/earlephilhower/pico-quick-toolchain/releases/download/1.3.4-a/x86_64-w64-mingw32.arm-none-eabi-ff58458.220606.zip",
                     "archiveFileName": "x86_64-w64-mingw32.arm-none-eabi-ff58458.220606.zip",
                     "checksum": "SHA-256:54258d573e65c05b322764d1f840f0510b34e88ac20b1cdc776cca401d9dd03a",
                     "size": "110394164"
                  }
               ]
            },
            {
               "version": "1.3.4-a-ff58458",
               "name": "pqt-elf2uf2",
               "systems": [
                  {
                     "host": "aarch64-linux-gnu",
                     "url": "https://github.com/earlephilhower/pico-quick-toolchain/releases/download/1.3.4-a/aarch64-linux-gnu.elf2uf2-2062372.220606.tar.gz",
                     "archiveFileName": "aarch64-linux-gnu.elf2uf2-2062372.220606.tar.gz",
                     "checksum": "SHA-256:32f579252082100e89597f206bc8a43a32cf91488385fdfe0ca1764acafb7c3b",
                     "size": "79853"
                  },
                  {
                     "host": "arm-linux-gnueabihf",
                     "url": "https://github.com/earlephilhower/pico-quick-toolchain/releases/download/1.3.4-a/arm-linux-gnueabihf.elf2uf2-2062372.220606.tar.gz",
                     "archiveFileName": "arm-linux-gnueabihf.elf2uf2-2062372.220606.tar.gz",
                     "checksum": "SHA-256:4dfc5c403868dd2dbfdbcc869c76c54256e2f751bb1f53a95360f2788547ba67",
                     "size": "54252"
                  },
                  {
                     "host": "i686-pc-linux-gnu",
                     "url": "https://github.com/earlephilhower/pico-quick-toolchain/releases/download/1.3.4-a/i686-linux-gnu.elf2uf2-2062372.220606.tar.gz",
                     "archiveFileName": "i686-linux-gnu.elf2uf2-2062372.220606.tar.gz",
                     "checksum": "SHA-256:cd8c90576c11b8eecfb254c3e8871815a332540bf33b01b31ae71cf44b2450be",
                     "size": "87893"
                  },
                  {
                     "host": "i686-mingw32",
                     "url": "https://github.com/earlephilhower/pico-quick-toolchain/releases/download/1.3.4-a/i686-w64-mingw32.elf2uf2-2062372.220606.zip",
                     "archiveFileName": "i686-w64-mingw32.elf2uf2-2062372.220606.zip",
                     "checksum": "SHA-256:7452f004e99905c1e00aa47eff9cd044125fa6be1db31e70dd8da1e36b40bfab",
                     "size": "70405"
                  },
                  {
                     "host": "x86_64-apple-darwin",
                     "url": "https://github.com/earlephilhower/pico-quick-toolchain/releases/download/1.3.4-a/x86_64-apple-darwin14.elf2uf2-2062372.220606.tar.gz",
                     "archiveFileName": "x86_64-apple-darwin14.elf2uf2-2062372.220606.tar.gz",
                     "checksum": "SHA-256:a81b7de886796992f1c7465a0c0d294f48d86b09dbf62a923cf1facff744caa7",
                     "size": "81984"
                  },
                  {
                     "host": "x86_64-pc-linux-gnu",
                     "url": "https://github.com/earlephilhower/pico-quick-toolchain/releases/download/1.3.4-a/x86_64-linux-gnu.elf2uf2-2062372.220606.tar.gz",
                     "archiveFileName": "x86_64-linux-gnu.elf2uf2-2062372.220606.tar.gz",
                     "checksum": "SHA-256:1949d8e0459e25e1e22b03331ac451ab4441a0bfc72cf5caa38dd4d00d878967",
                     "size": "79586"
                  },
                  {
                     "host": "x86_64-mingw32",
                     "url": "https://github.com/earlephilhower/pico-quick-toolchain/releases/download/1.3.4-a/x86_64-w64-mingw32.elf2uf2-2062372.220606.zip",
                     "archiveFileName": "x86_64-w64-mingw32.elf2uf2-2062372.220606.zip",
                     "checksum": "SHA-256:621d2a46a6b2f3ef28c0503bd58024af319ee706c868442d0f1eae80e9c0c96c",
                     "size": "78279"
                  }
               ]
            },
            {
               "version": "1.3.4-a-ff58458",
               "name": "pqt-pioasm",
               "systems": [
                  {
                     "host": "aarch64-linux-gnu",
                     "url": "https://github.com/earlephilhower/pico-quick-toolchain/releases/download/1.3.4-a/aarch64-linux-gnu.pioasm-2062372.220606.tar.gz",
                     "archiveFileName": "aarch64-linux-gnu.pioasm-2062372.220606.tar.gz",
                     "checksum": "SHA-256:327ff39e7c63e1223ed18c9fbba49ce0fbf5310cab170b3842a8d8ccc2db18e9",
                     "size": "453559"
                  },
                  {
                     "host": "arm-linux-gnueabihf",
                     "url": "https://github.com/earlephilhower/pico-quick-toolchain/releases/download/1.3.4-a/arm-linux-gnueabihf.pioasm-2062372.220606.tar.gz",
                     "archiveFileName": "arm-linux-gnueabihf.pioasm-2062372.220606.tar.gz",
                     "checksum": "SHA-256:53571f1897320e7097be5a3ebddcf80c16b203fe9684c840d20e5431cba25b8a",
                     "size": "360567"
                  },
                  {
                     "host": "i686-pc-linux-gnu",
                     "url": "https://github.com/earlephilhower/pico-quick-toolchain/releases/download/1.3.4-a/i686-linux-gnu.pioasm-2062372.220606.tar.gz",
                     "archiveFileName": "i686-linux-gnu.pioasm-2062372.220606.tar.gz",
                     "checksum": "SHA-256:6d49b9e4f3c89d3baf4babdad3f79cbd8ffc13d3880b7c251f6db46d58090891",
                     "size": "511401"
                  },
                  {
                     "host": "i686-mingw32",
                     "url": "https://github.com/earlephilhower/pico-quick-toolchain/releases/download/1.3.4-a/i686-w64-mingw32.pioasm-2062372.220606.zip",
                     "archiveFileName": "i686-w64-mingw32.pioasm-2062372.220606.zip",
                     "checksum": "SHA-256:ce0a890a34fde7ddc9a50ed0948a37c46f5372dbcf41c8ba21dbaa470e72863b",
                     "size": "385748"
                  },
                  {
                     "host": "x86_64-apple-darwin",
                     "url": "https://github.com/earlephilhower/pico-quick-toolchain/releases/download/1.3.4-a/x86_64-apple-darwin14.pioasm-2062372.220606.tar.gz",
                     "archiveFileName": "x86_64-apple-darwin14.pioasm-2062372.220606.tar.gz",
                     "checksum": "SHA-256:ef260c13629a58e9b769e5569cf8fe76c3a4ffd35afbaf8e7420a172bde9a90b",
                     "size": "480494"
                  },
                  {
                     "host": "x86_64-pc-linux-gnu",
                     "url": "https://github.com/earlephilhower/pico-quick-toolchain/releases/download/1.3.4-a/x86_64-linux-gnu.pioasm-2062372.220606.tar.gz",
                     "archiveFileName": "x86_64-linux-gnu.pioasm-2062372.220606.tar.gz",
                     "checksum": "SHA-256:33afe56bdaff8e62125129e96888d62684085ec27f378ac3c02b89e627cb82e0",
                     "size": "458729"
                  },
                  {
                     "host": "x86_64-mingw32",
                     "url": "https://github.com/earlephilhower/pico-quick-toolchain/releases/download/1.3.4-a/x86_64-w64-mingw32.pioasm-2062372.220606.zip",
                     "archiveFileName": "x86_64-w64-mingw32.pioasm-2062372.220606.zip",
                     "checksum": "SHA-256:d71d27c01256d84140317030a4e3c20860f00c69c5f6b627f744085a12e1f565",
                     "size": "408649"
                  }
               ]
            },
            {
               "version": "1.3.4-a-ff58458",
               "name": "pqt-mklittlefs",
               "systems": [
                  {
                     "host": "aarch64-linux-gnu",
                     "url": "https://github.com/earlephilhower/pico-quick-toolchain/releases/download/1.3.4-a/aarch64-linux-gnu.mklittlefs-affa497.220606.tar.gz",
                     "archiveFileName": "aarch64-linux-gnu.mklittlefs-affa497.220606.tar.gz",
                     "checksum": "SHA-256:4c7158fa399acef5a826e151d5d64015eeec5762e359ef01afb96b8a5b73d276",
                     "size": "47274"
                  },
                  {
                     "host": "arm-linux-gnueabihf",
                     "url": "https://github.com/earlephilhower/pico-quick-toolchain/releases/download/1.3.4-a/arm-linux-gnueabihf.mklittlefs-affa497.220606.tar.gz",
                     "archiveFileName": "arm-linux-gnueabihf.mklittlefs-affa497.220606.tar.gz",
                     "checksum": "SHA-256:9327e16fffa62c8fabb0c730da5544be774fb35b93110dd987132b3e0faa53f9",
                     "size": "40813"
                  },
                  {
                     "host": "i686-pc-linux-gnu",
                     "url": "https://github.com/earlephilhower/pico-quick-toolchain/releases/download/1.3.4-a/i686-linux-gnu.mklittlefs-affa497.220606.tar.gz",
                     "archiveFileName": "i686-linux-gnu.mklittlefs-affa497.220606.tar.gz",
                     "checksum": "SHA-256:48fb81af08afb8bd3407018b7596553597381809354a9a84b65233f48071c475",
                     "size": "50914"
                  },
                  {
                     "host": "i686-mingw32",
                     "url": "https://github.com/earlephilhower/pico-quick-toolchain/releases/download/1.3.4-a/i686-w64-mingw32.mklittlefs-affa497.220606.zip",
                     "archiveFileName": "i686-w64-mingw32.mklittlefs-affa497.220606.zip",
                     "checksum": "SHA-256:8d59c58cc586b6380a86f17f67bb6d886eaaa7b7e290847110ebeec3081f5ae8",
                     "size": "334050"
                  },
                  {
                     "host": "x86_64-apple-darwin",
                     "url": "https://github.com/earlephilhower/pico-quick-toolchain/releases/download/1.3.4-a/x86_64-apple-darwin14.mklittlefs-affa497.220606.tar.gz",
                     "archiveFileName": "x86_64-apple-darwin14.mklittlefs-affa497.220606.tar.gz",
                     "checksum": "SHA-256:3ddad4842da0401e6d87f1954df9c7b30c24a08b3c119133c865f6186c8b51c4",
                     "size": "365758"
                  },
                  {
                     "host": "x86_64-pc-linux-gnu",
                     "url": "https://github.com/earlephilhower/pico-quick-toolchain/releases/download/1.3.4-a/x86_64-linux-gnu.mklittlefs-affa497.220606.tar.gz",
                     "archiveFileName": "x86_64-linux-gnu.mklittlefs-affa497.220606.tar.gz",
                     "checksum": "SHA-256:0dadbc888080d74e9320c8fbb2248a352bb9628370ef9f626b5b1755d80fadde",
                     "size": "49774"
                  },
                  {
                     "host": "x86_64-mingw32",
                     "url": "https://github.com/earlephilhower/pico-quick-toolchain/releases/download/1.3.4-a/x86_64-w64-mingw32.mklittlefs-affa497.220606.zip",
                     "archiveFileName": "x86_64-w64-mingw32.mklittlefs-affa497.220606.zip",
                     "checksum": "SHA-256:a7d9b07d90e0851bf1c4deea00e193f6343a74fa4117d63ff9089cbd11173f52",
                     "size": "347601"
                  }
               ]
            }
         ]
      }
   ]
}